tiamat/__init__.py
tiamat/array.py
tiamat/cache.py
tiamat/cli.py
tiamat/constants.py
tiamat/errors.py
tiamat/io.py
tiamat/pipeline.py
tiamat/serialization.py
tiamat/metadata/__init__.py
tiamat/metadata/dimensions.py
tiamat/metadata/metadata.py
tiamat/readers/__init__.py
tiamat/readers/factory.py
tiamat/readers/generic.py
tiamat/readers/memory.py
tiamat/readers/nifti.py
tiamat/readers/pipeline.py
tiamat/readers/processing.py
tiamat/readers/protocol.py
tiamat/readers/stack.py
tiamat/readers/zarr.py
tiamat/transformers/__init__.py
tiamat/transformers/access.py
tiamat/transformers/affine.py
tiamat/transformers/axes.py
tiamat/transformers/color.py
tiamat/transformers/coordinates.py
tiamat/transformers/dfield.py
tiamat/transformers/metadata.py
tiamat/transformers/normalization.py
tiamat/transformers/protocol.py
tiamat/transformers/view.py
tiamat_python-0.1.10.dist-info/licenses/LICENSE
tiamat_python-0.1.10.dist-info/METADATA
tiamat_python-0.1.10.dist-info/WHEEL
tiamat_python-0.1.10.dist-info/entry_points.txt
tiamat_python-0.1.10.dist-info/top_level.txt
tiamat_python-0.1.10.dist-info/RECORD
