Metadata-Version: 2.4
Name: tiamat-python
Version: 0.1.10
Summary: Tiled Image Access, Manipulation, and Analysis Toolkit
Author-email: "Big Data Analytics Group, Forschungszentrum Juelich, Institute of Neuroscience and Medicine (INM-1)" <inm1-bda@fz-juelich.de>
License: 
Project-URL: homepage, https://www.fz-juelich.de/de/inm/inm-1
Project-URL: documentation, https://jugit.fz-juelich.de/inm-1/bda/software/data_access/tiamat/tiamat/-/blob/master/README.md?ref_type=heads
Project-URL: repository, https://jugit.fz-juelich.de/inm-1/bda/software/data_access/tiamat/tiamat
Classifier: Programming Language :: Python :: 3
Classifier: Programming Language :: Python :: 3 :: Only
Classifier: Programming Language :: Python :: 3.10
Classifier: Programming Language :: Python :: 3.11
Classifier: Programming Language :: Python :: 3.12
Classifier: License :: OSI Approved :: MIT License
Classifier: Operating System :: POSIX :: Linux
Classifier: Topic :: Scientific/Engineering
Requires-Python: >=3.10
License-File: LICENSE
Requires-Dist: click
Requires-Dist: numpy>=1.25.0
Requires-Dist: matplotlib
Requires-Dist: opencv-python-headless>=4.8.1
Requires-Dist: imageio
Requires-Dist: nibabel
Requires-Dist: scipy
Provides-Extra: dev
Requires-Dist: autopep8; extra == "dev"
Requires-Dist: flake8; extra == "dev"
Requires-Dist: pre-commit; extra == "dev"
Requires-Dist: pytest; extra == "dev"
Provides-Extra: zarr
Requires-Dist: zarr; extra == "zarr"
Dynamic: license-file
